odoo/addons/crm_assign_project/README.rst
odoo/addons/crm_assign_project/__init__.py
odoo/addons/crm_assign_project/__manifest__.py
odoo/addons/crm_assign_project/i18n/es.po
odoo/addons/crm_assign_project/models/__init__.py
odoo/addons/crm_assign_project/models/crm_lead.py
odoo/addons/crm_assign_project/models/crm_team.py
odoo/addons/crm_assign_project/readme/CONFIGURE.md
odoo/addons/crm_assign_project/readme/CONTRIBUTORS.md
odoo/addons/crm_assign_project/readme/DESCRIPTION.md
odoo/addons/crm_assign_project/readme/ROADMAP.md
odoo/addons/crm_assign_project/readme/USAGE.md
odoo/addons/crm_assign_project/static/description/icon.png
odoo/addons/crm_assign_project/static/description/index.html
odoo/addons/crm_assign_project/tests/__init__.py
odoo/addons/crm_assign_project/tests/test_crm_assign_project.py
odoo/addons/crm_assign_project/views/crm_team_views.xml
odoo_addon_crm_assign_project-17.0.1.0.0.dist-info/METADATA
odoo_addon_crm_assign_project-17.0.1.0.0.dist-info/WHEEL
odoo_addon_crm_assign_project-17.0.1.0.0.dist-info/top_level.txt
odoo_addon_crm_assign_project-17.0.1.0.0.dist-info/RECORD
