Metadata-Version: 2.1
Name: odoo-addon-crm_assign_project
Version: 17.0.1.0.0
Requires-Python: >=3.10
Requires-Dist: odoo-addon-crm_timesheet>=17.0dev,<17.1dev
Requires-Dist: odoo>=17.0a,<17.1dev
Summary: Automatically assign project to CRM lead.
Home-page: https://github.com/sygel-technology/sy-crm
License: AGPL-3
Author: Sygel, Odoo Community Association (OCA)
Author-email: support@odoo-community.org
Classifier: Programming Language :: Python
Classifier: Framework :: Odoo
Classifier: Framework :: Odoo :: 17.0
Classifier: License :: OSI Approved :: GNU Affero General Public License v3
